mcrpc/__init__.py
mcrpc/base.py
mcrpc/client.py
mcrpc/client.pyi
mcrpc/client.tpl
mcrpc/codegen.py
mcrpc/exceptions.py
mcrpc/lib.py
mcrpc/responses.py
mcrpc-2.0.6.0.dist-info/LICENSE
mcrpc-2.0.6.0.dist-info/WHEEL
mcrpc-2.0.6.0.dist-info/METADATA
mcrpc-2.0.6.0.dist-info/RECORD
