Metadata-Version: 2.1
Name: mcrpc
Version: 2.0.6.0
Summary: mcrpc: MultiChain RPC Library
Home-page: https://github.com/coblo/mcrpc
License: GPL-3.0
Keywords: mcrpc,coblo,client,rpc,multichain,api,content blockchain
Author: titusz
Author-email: tp@py7.de
Requires-Python: >=3.6,<4.0
Classifier: Development Status :: 5 - Production/Stable
Classifier: Intended Audience :: Developers
Classifier: License :: OSI Approved :: GNU General Public License v3 (GPLv3)
Classifier: Natural Language :: English
Classifier: Programming Language :: Python :: 3
Classifier: Programming Language :: Python :: 3.6
Classifier: Programming Language :: Python :: 3.7
Classifier: Programming Language :: Python :: 3.8
Requires-Dist: appdirs (>=1.4.3,<2.0.0)
Requires-Dist: configobj (>=5.0.6,<6.0.0)
Requires-Dist: requests (>=2.23.0,<3.0.0)
Requires-Dist: simplejson (>=3.17.0,<4.0.0)
Project-URL: Repository, https://github.com/coblo/mcrpc
